flask_swaggerui/__init__.py
flask_swaggerui/functions.py
flask_swaggerui/static/LICENSE
flask_swaggerui/static/README.md
flask_swaggerui/static/index.html
flask_swaggerui/static/o2c.html
flask_swaggerui/static/swagger-ui.js
flask_swaggerui/static/swagger-ui.min.js
flask_swaggerui/static/css/print.css
flask_swaggerui/static/css/reset.css
flask_swaggerui/static/css/screen.css
flask_swaggerui/static/css/style.css
flask_swaggerui/static/css/typography.css
flask_swaggerui/static/fonts/DroidSans-Bold.ttf
flask_swaggerui/static/fonts/DroidSans.ttf
flask_swaggerui/static/images/collapse.gif
flask_swaggerui/static/images/expand.gif
flask_swaggerui/static/images/explorer_icons.png
flask_swaggerui/static/images/favicon-16x16.png
flask_swaggerui/static/images/favicon-32x32.png
flask_swaggerui/static/images/favicon.ico
flask_swaggerui/static/images/logo_small.png
flask_swaggerui/static/images/pet_store_api.png
flask_swaggerui/static/images/throbber.gif
flask_swaggerui/static/images/wordnik_api.png
flask_swaggerui/static/lang/en.js
flask_swaggerui/static/lang/es.js
flask_swaggerui/static/lang/fr.js
flask_swaggerui/static/lang/geo.js
flask_swaggerui/static/lang/it.js
flask_swaggerui/static/lang/ja.js
flask_swaggerui/static/lang/pl.js
flask_swaggerui/static/lang/pt.js
flask_swaggerui/static/lang/ru.js
flask_swaggerui/static/lang/tr.js
flask_swaggerui/static/lang/translator.js
flask_swaggerui/static/lang/zh-cn.js
flask_swaggerui/static/lib/backbone-min.js
flask_swaggerui/static/lib/handlebars-2.0.0.js
flask_swaggerui/static/lib/highlight.9.1.0.pack.js
flask_swaggerui/static/lib/highlight.9.1.0.pack_extended.js
flask_swaggerui/static/lib/jquery-1.8.0.min.js
flask_swaggerui/static/lib/jquery.ba-bbq.min.js
flask_swaggerui/static/lib/jquery.slideto.min.js
flask_swaggerui/static/lib/jquery.wiggle.min.js
flask_swaggerui/static/lib/js-yaml.min.js
flask_swaggerui/static/lib/jsoneditor.min.js
flask_swaggerui/static/lib/lodash.min.js
flask_swaggerui-0.0.1.dist-info/DESCRIPTION.rst
flask_swaggerui-0.0.1.dist-info/METADATA
flask_swaggerui-0.0.1.dist-info/RECORD
flask_swaggerui-0.0.1.dist-info/WHEEL
flask_swaggerui-0.0.1.dist-info/metadata.json
flask_swaggerui-0.0.1.dist-info/top_level.txt
