Metadata-Version: 2.0
Name: flask-swaggerui
Version: 0.0.1
Summary: This library provides python Flask utilities and static assets for rendering Swagger UI
Home-page: http://pypi.python.org/pypi/flask-swaggerui
Author: Aaron Halfaker
Author-email: aaron.halfaker@gmail.com
License: The MIT License (MIT)
Requires-Dist: Flask
